Khronos-0.1.dist-info/DESCRIPTION.rst
Khronos-0.1.dist-info/METADATA
Khronos-0.1.dist-info/RECORD
Khronos-0.1.dist-info/WHEEL
Khronos-0.1.dist-info/metadata.json
Khronos-0.1.dist-info/top_level.txt
khronos/__init__.py
khronos/models/__init__.py
khronos/series/__init__.py
khronos/series/series_1d.py
khronos/stats/__init__.py
khronos/utils/__init__.py
khronos/utils/catch.py
khronos/utils/time_utils.py
