Metadata-Version: 2.0
Name: Khronos
Version: 0.1
Summary: Time series analytics for Python
Home-page: https://github.com/PForet/khronos
Author: Pierre Foret
Author-email: pierre_foret@berkeley.edu
License: MIT
Platform: UNKNOWN
Classifier: Development Status :: 1 - Planning
Classifier: Intended Audience :: Developers
Classifier: Intended Audience :: Education
Classifier: Intended Audience :: Science/Research
Classifier: License :: OSI Approved :: MIT License
Classifier: Programming Language :: Python :: 2
Classifier: Programming Language :: Python :: 2.7
Classifier: Programming Language :: Python :: 3
Classifier: Programming Language :: Python :: 3.6
Classifier: Topic :: Software Development :: Libraries
Classifier: Topic :: Software Development :: Libraries :: Python Modules
Requires-Dist: datetime
Requires-Dist: numpy
Requires-Dist: scipy
